{
      "brief_title": [
            "erlotinib",
            "tarceva",
            "trademark",
            "treat",
            "patient",
            "advance",
            "cell",
            "lung",
            "cancer"
      ],
      "brief_summary": [
            "purpose",
            "study",
            "determine",
            "erlotinib",
            "improve",
            "disease",
            "dose",
            "produce",
            "characteristic",
            "rash",
            "patient",
            "advance",
            "cell",
            "lung",
            "cancer"
      ],
      "detailed_description": [
            "patient",
            "0",
            "1",
            "performance",
            "status",
            "ecog",
            "scale",
            "eligible"
      ],
      "condition": [
            "non",
            "small",
            "cell",
            "lung",
            "cancer",
            "prior",
            "chemotherapy"
      ],
      "intervention_type": [
            "Drug"
      ],
      "intervention_name": [
            "Tarceva (Trademark) (erlotinib HCl, OSI-774)"
      ],
      "description": [
            "dose",
            "escalation",
            "oral",
            "single",
            "agent",
            "daily",
            "erlotinib",
            "intolerable",
            "rash"
      ],
      "arm_group_label": [
            "erlotinib"
      ],
      "criteria": [
            "inclusion",
            "criterion",
            "confirm",
            "diagnosis",
            "stage",
            "iiib",
            "iv",
            "cell",
            "lung",
            "cancer",
            "histological",
            "cytological",
            "receive",
            "prior",
            "chemotherapy",
            "treatment",
            "advance",
            "metastatic",
            "cell",
            "lung",
            "cancer",
            "measurable",
            "disease",
            "per",
            "recist",
            "criterion",
            "adequate",
            "bone",
            "marrow",
            "hepatic",
            "renal",
            "function",
            "exclusion",
            "criterion",
            "breast",
            "cancer",
            "skin",
            "cancer",
            "time",
            "past",
            "cancer",
            "past",
            "5",
            "year",
            "brain",
            "metastasis",
            "unstable",
            "require",
            "steroid",
            "require",
            "radiation",
            "last",
            "28",
            "day",
            "know",
            "hypersensitivity",
            "minocycline",
            "history",
            "serious",
            "cardiac",
            "disease",
            "control",
            "serious",
            "eye",
            "condition",
            "prior",
            "treatment",
            "inhibitor",
            "egfr",
            "kind"
      ],
      "gender": "All",
      "minimum_age": [
            "18",
            "year"
      ],
      "maximum_age": [],
      "healthy_volunteers": "No",
      "keyword": [],
      "mesh_term": [
            "neoplasm",
            "lung",
            "hydrochloride"
      ],
      "id": "NCT00072631"
}