{
      "brief_title": [
            "john",
            "wort",
            "versus",
            "placebo",
            "social",
            "phobia"
      ],
      "brief_summary": [
            "purpose",
            "study",
            "determine",
            "effectiveness",
            "john",
            "wort",
            "compare",
            "placebo",
            "inactive",
            "substance",
            "treatment",
            "outpatient",
            "social",
            "phobia"
      ],
      "detailed_description": [
            "social",
            "phobia",
            "prevalent",
            "debilitate",
            "condition",
            "lifetime",
            "prevalence",
            "rate",
            "percent",
            "socially",
            "phobic",
            "patient",
            "find",
            "functionally",
            "impair",
            "area",
            "education",
            "employment",
            "social",
            "relationship",
            "poorer",
            "quality",
            "life",
            "increase",
            "suicidal",
            "ideation",
            "psychiatric",
            "comorbidity",
            "study",
            "find",
            "benzodiazepine",
            "selective",
            "maoi",
            "inhibitor",
            "several",
            "ssri",
            "anticonvulsant",
            "pregabalin",
            "gabapentin",
            "effective",
            "however",
            "side",
            "effect",
            "compound",
            "suggest",
            "need",
            "better",
            "tolerate",
            "compound",
            "paroxetine",
            "trial",
            "drug",
            "fda",
            "approve",
            "indication",
            "27",
            "percent",
            "report",
            "somnolence",
            "26",
            "percent",
            "nausea",
            "37",
            "percent",
            "male",
            "report",
            "delay",
            "ejaculation",
            "34",
            "percent",
            "patient",
            "discontinue",
            "trial",
            "early",
            "considerable",
            "worldwide",
            "interest",
            "john",
            "wort",
            "sjw",
            "hypericum",
            "perforatum",
            "treatment",
            "mild",
            "moderate",
            "depression",
            "23",
            "randomize",
            "trial",
            "suggest",
            "sjw",
            "effective",
            "placebo",
            "treatment",
            "outpatient",
            "mild",
            "moderate",
            "depression",
            "sjw",
            "well",
            "tolerate",
            "mild",
            "side",
            "effect",
            "observe",
            "percent",
            "case",
            "large",
            "3250",
            "patient",
            "drug",
            "monitor",
            "study",
            "pharmacokinetic",
            "study",
            "find",
            "hypericum",
            "affinity",
            "serotonin",
            "dopamine",
            "gaba",
            "alpha",
            "gaba",
            "beta",
            "receptor",
            "implicate",
            "social",
            "phobia",
            "thus",
            "suggestion",
            "sjw",
            "may",
            "effective",
            "disorder",
            "double",
            "blind",
            "trial",
            "design",
            "generate",
            "effect",
            "size",
            "data",
            "use",
            "determine",
            "sample",
            "size",
            "need",
            "power",
            "definitive",
            "study",
            "forty",
            "patient",
            "randomize",
            "either",
            "sjw",
            "li",
            "160",
            "match",
            "placebo",
            "design",
            "start",
            "300",
            "mg",
            "tid",
            "maximum",
            "1800",
            "mg",
            "total",
            "per",
            "day",
            "analysis",
            "employ",
            "subject",
            "evaluate",
            "weekly",
            "two",
            "week",
            "thereafter",
            "primary",
            "outcome",
            "measure",
            "change",
            "baseline",
            "endpoint",
            "liebowitz",
            "social",
            "anxiety",
            "scale"
      ],
      "condition": [
            "phobic",
            "disorder"
      ],
      "intervention_type": [
            "drug"
      ],
      "intervention_name": [
            "john",
            "wort"
      ],
      "criteria": [
            "inclusion",
            "criterion",
            "female",
            "patient",
            "least",
            "2",
            "year",
            "surgically",
            "sterile",
            "practice",
            "medically",
            "acceptable",
            "method",
            "contraception",
            "meet",
            "criterion",
            "social",
            "phobia",
            "generalize",
            "subtype",
            "last",
            "12",
            "month",
            "duration",
            "phone",
            "screen",
            "determine",
            "exclusion",
            "criterion",
            "primary",
            "diagnosis",
            "major",
            "depression",
            "dysthymia",
            "panic",
            "disorder",
            "schizophrenia",
            "disorder",
            "bipolar",
            "disorder",
            "ptsd",
            "substance",
            "abuse",
            "dependence",
            "past",
            "6",
            "month",
            "vascular",
            "dementia",
            "primary",
            "degenerative",
            "dementia",
            "alzheimer",
            "type",
            "treatment",
            "maoi",
            "tcas",
            "ssri",
            "venlafaxine",
            "nefazodone",
            "remeron",
            "citalopram",
            "bupropion",
            "within",
            "14",
            "day",
            "first",
            "visit",
            "fluoxetine",
            "within",
            "14",
            "day",
            "first",
            "visit",
            "failure",
            "respond",
            "least",
            "two",
            "adequate",
            "antidepressant",
            "trial",
            "social",
            "anxiety",
            "investigational",
            "drug",
            "within",
            "30",
            "day",
            "baseline",
            "know",
            "allergy",
            "hypersensitivity",
            "john",
            "wort",
            "currently",
            "behavior",
            "therapy",
            "social",
            "phobia",
            "inquiry",
            "undergo",
            "phone",
            "screen",
            "determine",
            "whether",
            "meet",
            "eligiblity",
            "requirement"
      ],
      "gender": [],
      "minimum_age": [
            "18",
            "year"
      ],
      "maximum_age": [
            "65",
            "year"
      ],
      "healthy_volunteers": false,
      "id": "NCT00035412.xml"
}