{
      "brief_title": [
            "psychosocial",
            "determinant",
            "nutrient",
            "intake",
            "girl"
      ],
      "brief_summary": [
            "better",
            "understand",
            "determinant",
            "nutrient",
            "intake",
            "black",
            "white",
            "adolescent",
            "girl",
            "examine",
            "effect",
            "nutrient",
            "intake",
            "eat",
            "behavior",
            "obesity",
            "significant",
            "risk",
            "factor",
            "cvd"
      ],
      "detailed_description": [
            "background",
            "study",
            "document",
            "importance",
            "eat",
            "behavior",
            "modifiable",
            "risk",
            "factor",
            "development",
            "obesity",
            "cardiovascular",
            "disease",
            "cvd",
            "burden",
            "obesity",
            "cvd",
            "equally",
            "distribute",
            "population",
            "woman",
            "ethnic",
            "minority",
            "population",
            "particularly",
            "likely",
            "obese",
            "higher",
            "rat",
            "cvd",
            "stroke",
            "white",
            "woman",
            "design",
            "narrative",
            "study",
            "determine",
            "extent",
            "psychological",
            "familial",
            "factor",
            "contribute",
            "nutrient",
            "intake",
            "black",
            "white",
            "girl",
            "beyond",
            "effect",
            "ethnicity",
            "socioeconomic",
            "factor",
            "specifically",
            "aim",
            "project",
            "follow",
            "1",
            "provide",
            "detail",
            "developmental",
            "description",
            "eat",
            "behavior",
            "nutrient",
            "intake",
            "black",
            "white",
            "girl",
            "examine",
            "cluster",
            "certain",
            "eat",
            "behavior",
            "skip",
            "meal",
            "snack",
            "eat",
            "pattern",
            "2",
            "determine",
            "clinical",
            "significance",
            "eat",
            "behavior",
            "eat",
            "pattern",
            "examine",
            "contribution",
            "nutrient",
            "intake",
            "development",
            "obesity",
            "3",
            "examine",
            "role",
            "psychological",
            "familial",
            "factor",
            "determinant",
            "eat",
            "behavior",
            "eat",
            "pattern",
            "nutrient",
            "intake",
            "obesity",
            "black",
            "white",
            "girl",
            "capitalize",
            "upon",
            "availability",
            "extensive",
            "data",
            "collect",
            "prospectively",
            "among",
            "exceptionally",
            "cohort",
            "black",
            "white",
            "female",
            "period",
            "age",
            "age",
            "study",
            "apply",
            "innovative",
            "analytic",
            "procedure",
            "scientific",
            "understand",
            "determinant",
            "nutrient",
            "intake",
            "eat",
            "behavior",
            "adolescent",
            "girl",
            "participant",
            "ass",
            "annually",
            "ten",
            "year",
            "part",
            "national",
            "heart",
            "lung",
            "blood",
            "institute",
            "growth",
            "health",
            "study",
            "nghs",
            "measurement",
            "anthropometry",
            "food",
            "intake",
            "eat",
            "weight",
            "relate",
            "attitude",
            "behavior",
            "family",
            "cohesion",
            "parent",
            "also",
            "provide",
            "information",
            "weight",
            "eat",
            "family",
            "environment",
            "two",
            "assessment",
            "subsequent",
            "study",
            "sample",
            "structure",
            "clinical",
            "interview",
            "conduct",
            "determine",
            "history",
            "psychiatric",
            "disorder",
            "risk",
            "factor",
            "eat",
            "disorder",
            "adult",
            "weight",
            "also",
            "measure"
      ],
      "condition": [
            "disease",
            "disease"
      ],
      "criteria": [
            "eligibility",
            "criterion"
      ],
      "gender": "Female",
      "minimum_age": [
            "9",
            "year"
      ],
      "maximum_age": [
            "23",
            "year"
      ],
      "healthy_volunteers": "No",
      "mesh_term": [
            "disease",
            "disease"
      ],
      "id": "NCT00046579"
}