{
      "brief_title": [
            "treatment",
            "adult",
            "attention",
            "deficit",
            "hyperactivity",
            "disorder",
            "adhd",
            "methadone",
            "patient",
            "1"
      ],
      "brief_summary": [
            "purpose",
            "study",
            "treat",
            "adult",
            "attention",
            "deficit",
            "hyperactivity",
            "disorder",
            "adhd",
            "methadone",
            "patient"
      ],
      "detailed_description": [
            "project",
            "three",
            "arm",
            "randomize",
            "trial",
            "compare",
            "efficacy",
            "mph",
            "bpr",
            "relative",
            "placebo",
            "treat",
            "persistent",
            "adhd",
            "patient",
            "one",
            "hundred",
            "twenty",
            "subject",
            "randomize",
            "receive",
            "either",
            "mph",
            "bpr",
            "placebo",
            "equal",
            "probability",
            "randomization",
            "stratify",
            "site",
            "whether",
            "cocaine",
            "also",
            "use",
            "efficacy",
            "measure",
            "treatment",
            "retention",
            "reduction",
            "illicit",
            "drug",
            "use",
            "drug",
            "crave",
            "improvement",
            "adhd",
            "symptom",
            "overall",
            "functional",
            "status"
      ],
      "condition": [
            "cocaine",
            "dependence"
      ],
      "intervention_type": [],
      "intervention_name": [
            "placebo"
      ],
      "description": [
            "placebo"
      ],
      "arm_group_label": [
            "placebo"
      ],
      "criteria": [
            "inclusion",
            "criterion",
            "individual",
            "meet",
            "criterion",
            "opiate",
            "dependence",
            "currently",
            "maintain",
            "methadone",
            "patient",
            "must",
            "meet",
            "criterion",
            "persistent",
            "adult",
            "adhd",
            "must",
            "stable",
            "methadone",
            "dose",
            "least",
            "3",
            "week",
            "individual",
            "positive",
            "hiv",
            "exclude",
            "exclusion",
            "criterion",
            "patient",
            "meet",
            "criterion",
            "current",
            "psychiatric",
            "disorder",
            "adhd",
            "substance",
            "abuse",
            "require",
            "psychiatric",
            "intervention",
            "patient",
            "physiologically",
            "dependent",
            "either",
            "sedative",
            "alcohol",
            "experience",
            "symptom",
            "require",
            "medical",
            "attention",
            "period",
            "abstinence",
            "significant",
            "reduction",
            "amount",
            "use",
            "individual",
            "diagnose",
            "form",
            "adult",
            "adhd",
            "persistent",
            "particularly",
            "adhd",
            "unstable",
            "medical",
            "condition",
            "might",
            "make",
            "participation",
            "hazardous",
            "include",
            "restrict",
            "uncontrolled",
            "hypertension",
            "sbp",
            "160",
            "dbp",
            "100",
            "pulse",
            "110",
            "uncontrolled",
            "liver",
            "disease",
            "uncontrolled",
            "diabetes",
            "acute",
            "hepatitis",
            "uncontrolled",
            "heart",
            "disease",
            "indicate",
            "history",
            "abnormal",
            "ecg",
            "glaucoma",
            "history",
            "urinary",
            "retention",
            "seizure",
            "advance",
            "aid",
            "include",
            "patient",
            "take",
            "prescription",
            "psychotropic",
            "medication",
            "methadone",
            "patient",
            "exhibit",
            "suicidal",
            "homicidal",
            "behavior",
            "within",
            "past",
            "two",
            "year",
            "patient",
            "know",
            "sensitivity",
            "mph",
            "bpr",
            "patient",
            "cognitive",
            "impairment",
            "read",
            "understand",
            "assessment",
            "form",
            "unaided",
            "severely",
            "disable",
            "comply",
            "requirement",
            "study",
            "patient",
            "unable",
            "give",
            "full",
            "inform",
            "consent",
            "patient",
            "history",
            "eat",
            "disorder",
            "patient",
            "recently",
            "convict",
            "violent",
            "crime",
            "last",
            "two",
            "year",
            "nurse",
            "mother",
            "pregnant",
            "woman"
      ],
      "gender": [],
      "minimum_age": [
            "18",
            "year"
      ],
      "maximum_age": [
            "60",
            "year"
      ],
      "healthy_volunteers": false,
      "id": "NCT00061087.xml"
}