{
      "brief_title": [
            "systolic",
            "pressure",
            "efficacy",
            "safety",
            "trial",
            "alagebrium",
            "spectrum"
      ],
      "brief_summary": [
            "study",
            "comprise",
            "hydrochlorothiazide",
            "run",
            "phase",
            "follow",
            "12",
            "week",
            "treatment",
            "phase",
            "follow",
            "2",
            "week",
            "hydrochlorothiazide",
            "treatment",
            "phase",
            "combine",
            "total",
            "duration",
            "patient",
            "participation",
            "approximately",
            "week",
            "four",
            "treatment",
            "group",
            "approximately",
            "equal",
            "size",
            "98",
            "comprise",
            "study",
            "population",
            "placebo",
            "various",
            "alagebrium",
            "dose",
            "group",
            "10",
            "50",
            "150"
      ],
      "condition": [
            "hypertension"
      ],
      "intervention_type": [
            "drug"
      ],
      "intervention_name": [
            "alagebrium",
            "chloride"
      ],
      "criteria": [
            "inclusion",
            "criterion",
            "men",
            "woman",
            "least",
            "45",
            "year",
            "age",
            "uncontrolled",
            "systolic",
            "hypertension",
            "measure",
            "office",
            "cuff",
            "ambulatory",
            "blood",
            "pressure",
            "monitor",
            "device",
            "willingness",
            "take",
            "current",
            "antihypertensive",
            "treatment",
            "place",
            "hydrochlorothiazide",
            "combination",
            "study",
            "medication",
            "exclusion",
            "criterion",
            "significant",
            "history",
            "systemic",
            "illness",
            "medical",
            "condition",
            "could",
            "lead",
            "difficulty",
            "comply",
            "protocol",
            "could",
            "confound",
            "interpretation",
            "data"
      ],
      "gender": [],
      "minimum_age": [
            "45",
            "year"
      ],
      "maximum_age": [],
      "healthy_volunteers": false,
      "id": "NCT00089713.xml"
}