{
      "brief_title": [
            "granulocyte",
            "transfusion",
            "study"
      ],
      "brief_summary": [
            "evaluate",
            "granulocyte",
            "transfusion",
            "therapy",
            "respect",
            "prophylactic",
            "therapeutic",
            "effectiveness",
            "prevent",
            "aid",
            "recovery",
            "infection",
            "study",
            "trial",
            "conduct",
            "simultaneously"
      ],
      "detailed_description": [
            "background",
            "infection",
            "remain",
            "major",
            "cause",
            "death",
            "patient",
            "receive",
            "chemotherapy",
            "malignant",
            "disease",
            "one",
            "approach",
            "problem",
            "septicemia",
            "high",
            "mortality",
            "patient",
            "therapeutic",
            "use",
            "granulocyte",
            "transfusion",
            "improvement",
            "collection",
            "technique",
            "employ",
            "continuous",
            "flow",
            "centrifugation",
            "permit",
            "collection",
            "granulocyte",
            "single",
            "normal",
            "donor",
            "sufficient",
            "number",
            "study",
            "application",
            "treatment",
            "infection",
            "granulocytopenic",
            "patient",
            "study",
            "demonstrate",
            "efficacy",
            "granulocyte",
            "transfusion",
            "adjunct",
            "therapy",
            "septicemia",
            "due",
            "gram",
            "negative",
            "microorganism",
            "associate",
            "granulocytopenia",
            "aim",
            "study",
            "determine",
            "1",
            "whether",
            "infection",
            "could",
            "prevent",
            "patient",
            "receive",
            "granulocyte",
            "prophylactically",
            "2",
            "whether",
            "recovery",
            "infection",
            "aid",
            "patient",
            "receive",
            "granulocyte",
            "therapeutically",
            "trial",
            "utilize",
            "control",
            "receive",
            "granulocyte",
            "four",
            "contract",
            "award",
            "september",
            "1976",
            "protocol",
            "design",
            "evaluate",
            "efficacy",
            "prophylactic",
            "granulocyte",
            "transfusion",
            "complete",
            "close",
            "1977",
            "protocol",
            "therapeutic",
            "trial",
            "complete",
            "april",
            "1978",
            "approximately",
            "90",
            "patient",
            "randomize",
            "prophylactic",
            "trial",
            "51",
            "therapeutic",
            "trial",
            "recruitment",
            "intervention",
            "phase",
            "end",
            "february",
            "1980",
            "trial",
            "conclude",
            "design",
            "narrative",
            "prophylactic",
            "trial",
            "therapeutic",
            "trial",
            "randomize",
            "sequential",
            "eligible",
            "patient",
            "randomize",
            "daily",
            "granulocyte",
            "transfusion",
            "granulocyte",
            "transfusion",
            "study",
            "completion",
            "date",
            "list",
            "record",
            "infer",
            "first",
            "publication",
            "list",
            "citation",
            "section",
            "study",
            "record"
      ],
      "condition": [
            "infection"
      ],
      "intervention_type": [
            "procedure"
      ],
      "intervention_name": [
            "leukocyte",
            "transfusion"
      ],
      "criteria": [
            "prophylactic",
            "trial",
            "male",
            "female",
            "12",
            "year",
            "older",
            "first",
            "induction",
            "phase",
            "chemotherapy",
            "acute",
            "leukemia",
            "severe",
            "neutropenia",
            "document",
            "infection",
            "therapeutic",
            "trial",
            "male",
            "female"
      ],
      "gender": [],
      "minimum_age": [
            "12",
            "year"
      ],
      "maximum_age": [],
      "healthy_volunteers": false,
      "id": "NCT00000581.xml"
}