{
      "brief_title": [
            "study",
            "daclizumab",
            "patient",
            "chronic",
            "persistent",
            "asthma"
      ],
      "brief_summary": [
            "purpose",
            "study",
            "evaluate",
            "investigational",
            "medication",
            "treat",
            "chronic",
            "persistent",
            "asthma",
            "research",
            "conduct",
            "22",
            "clinical",
            "research",
            "sit",
            "u",
            "open",
            "men",
            "woman",
            "age",
            "18",
            "70",
            "year",
            "old",
            "participant",
            "study",
            "number",
            "visit",
            "research",
            "site",
            "period",
            "care",
            "medication",
            "provide",
            "qualify",
            "participant",
            "cost",
            "include",
            "visit",
            "examination",
            "laboratory",
            "work"
      ],
      "condition": [],
      "intervention_type": [
            "Drug"
      ],
      "intervention_name": [
            "Daclizumab"
      ],
      "criteria": [
            "inclusion",
            "criterion",
            "history",
            "asthma",
            "6",
            "month",
            "history",
            "chronic",
            "persistent",
            "asthma",
            "require",
            "daily",
            "high",
            "dose",
            "inhale",
            "corticosteroid",
            "3",
            "month",
            "prior",
            "enrollment",
            "exclusion",
            "criterion",
            "patient",
            "10",
            "pack",
            "year",
            "smoke",
            "history",
            "smoke",
            "within",
            "12",
            "month",
            "study",
            "enrollment",
            "significant",
            "disease",
            "asthma"
      ],
      "gender": "All",
      "minimum_age": [
            "18",
            "year"
      ],
      "maximum_age": [
            "70",
            "year"
      ],
      "healthy_volunteers": "No",
      "keyword": [
            "zenapax"
      ],
      "mesh_term": [
            "g"
      ],
      "id": "NCT00028288"
}