{
      "brief_title": [
            "zoledronate",
            "treat",
            "patient",
            "solid",
            "tumor",
            "spread",
            "bone"
      ],
      "brief_summary": [
            "rationale",
            "zoledronate",
            "may",
            "help",
            "relieve",
            "symptom",
            "cause",
            "bone",
            "metastasis",
            "yet",
            "know",
            "zoledronate",
            "effective",
            "therapy",
            "relieve",
            "symptom",
            "bone",
            "metastasis",
            "prevent",
            "disease",
            "progression",
            "purpose",
            "randomize",
            "phase",
            "iii",
            "trial",
            "determine",
            "effectiveness",
            "zoledronate",
            "treat",
            "patient",
            "solid",
            "tumor",
            "spread",
            "bone"
      ],
      "detailed_description": [
            "objective",
            "ass",
            "safety",
            "efficacy",
            "zoledronate",
            "patient",
            "solid",
            "tumor",
            "cancer",
            "bone",
            "metastasis",
            "breast",
            "prostate",
            "cancer",
            "ii",
            "ass",
            "efficacy",
            "zoledronate",
            "prevent",
            "event",
            "include",
            "tumor",
            "induce",
            "hypercalcemia",
            "tih",
            "time",
            "first",
            "occurrence",
            "event",
            "tih",
            "skeletal",
            "morbidity",
            "rate",
            "time",
            "progression",
            "bone",
            "metastasis",
            "overall",
            "survival",
            "time",
            "overall",
            "disease",
            "progression",
            "patient",
            "iii",
            "ass",
            "quality",
            "life",
            "pain",
            "patient",
            "regimen",
            "outline",
            "randomize",
            "double",
            "blind",
            "placebo",
            "control",
            "multicenter",
            "study",
            "patient",
            "stratify",
            "two",
            "group",
            "patient",
            "lung",
            "cancer",
            "patient",
            "solid",
            "tumor",
            "cancer",
            "patient",
            "randomly",
            "assign",
            "receive",
            "1",
            "follow",
            "treatment",
            "arm",
            "patient",
            "receive",
            "intravenous",
            "zoledronate",
            "5",
            "minute",
            "every",
            "3",
            "week",
            "9",
            "month",
            "arm",
            "ii",
            "patient",
            "receive",
            "intravenous",
            "zoledronate",
            "higher",
            "dose",
            "5",
            "minute",
            "every",
            "3",
            "week",
            "9",
            "month",
            "arm",
            "iii",
            "patient",
            "receive",
            "intravenous",
            "placebo",
            "5",
            "minute",
            "every",
            "3",
            "week",
            "9",
            "month",
            "patient",
            "receive",
            "oral",
            "calcium",
            "daily",
            "oral",
            "multivitamin",
            "supplement",
            "quality",
            "life",
            "ass",
            "prior",
            "therapy",
            "month",
            "3",
            "6",
            "9",
            "patient",
            "follow",
            "every",
            "6",
            "month",
            "survival",
            "project",
            "accrual",
            "total",
            "600",
            "patient",
            "accrue",
            "study",
            "within",
            "12",
            "month"
      ],
      "condition": [
            "unspecified",
            "adult",
            "solid",
            "tumor",
            "protocol",
            "specific"
      ],
      "intervention_type": [
            "procedure"
      ],
      "intervention_name": [
            "assessment"
      ],
      "criteria": [
            "disease",
            "characteristic",
            "histologically",
            "cytologically",
            "confirm",
            "diagnosis",
            "cancer",
            "breast",
            "cancer",
            "multiple",
            "myeloma",
            "prostate",
            "cancer",
            "objective",
            "evidence",
            "bone",
            "metastasis",
            "discover",
            "within",
            "6",
            "week",
            "study",
            "entry",
            "patient",
            "screen",
            "present",
            "ecog",
            "score",
            "2",
            "study",
            "entry",
            "restriction",
            "bone",
            "metastasis",
            "patient",
            "ecog",
            "0",
            "1",
            "symptomatic",
            "brain",
            "metastasis",
            "patient",
            "characteristic",
            "age",
            "18",
            "performance",
            "status",
            "ecog",
            "life",
            "expectancy",
            "specify",
            "hematopoietic",
            "specify",
            "hepatic",
            "bilirubin",
            "greater",
            "liver",
            "metastasis",
            "renal",
            "creatinine",
            "greater",
            "calcium",
            "least",
            "le",
            "cardiovascular",
            "history",
            "severe",
            "cardiovascular",
            "disease",
            "within",
            "past",
            "6",
            "month",
            "congestive",
            "heart",
            "failure",
            "hypertension",
            "refractory",
            "treatment",
            "symptomatic",
            "coronary",
            "artery",
            "disease",
            "pregnant",
            "nurse",
            "negative",
            "pregnancy",
            "test",
            "fertile",
            "patient",
            "must",
            "use",
            "effective",
            "contraception",
            "history",
            "noncompliance",
            "medical",
            "regimen",
            "prior",
            "concurrent",
            "therapy",
            "biologic",
            "therapy",
            "concurrent",
            "biologic",
            "response",
            "modifier",
            "therapy",
            "allow",
            "concurrent",
            "market",
            "cytokine",
            "colony",
            "stimulate",
            "factor",
            "therapy",
            "allow",
            "chemotherapy",
            "concurrent",
            "market",
            "chemotherapy",
            "agent",
            "allow",
            "include",
            "open",
            "label",
            "cooperative",
            "trial",
            "supportive",
            "care",
            "endocrine",
            "therapy",
            "concurrent",
            "hormonal",
            "agent",
            "steroid",
            "therapy",
            "allow",
            "concurrent",
            "corticosteroid",
            "therapy",
            "allow",
            "chemotherapy",
            "induce",
            "spinal",
            "compression",
            "radiotherapy",
            "concurrent",
            "radiotherapy",
            "treat",
            "extraskeletal",
            "skeletal",
            "tumor",
            "sit",
            "allow",
            "surgery",
            "prior",
            "surgery",
            "treat",
            "prevent",
            "pathological",
            "fracture",
            "spinal",
            "cord",
            "compression",
            "allow",
            "least",
            "30",
            "day",
            "since",
            "prior",
            "investigational",
            "drug",
            "concurrent",
            "bisphosphonate",
            "agent",
            "least",
            "30",
            "day",
            "since",
            "prior",
            "bisphosphonate",
            "agent",
            "single",
            "exposure",
            "allow",
            "within",
            "prior",
            "12",
            "month"
      ],
      "gender": [],
      "minimum_age": [
            "18",
            "year"
      ],
      "maximum_age": [],
      "healthy_volunteers": false,
      "id": "NCT00003884.xml"
}