{
      "brief_title": [
            "study",
            "specimen",
            "obtain",
            "epilepsy",
            "surgery"
      ],
      "brief_summary": [
            "study",
            "collect",
            "brain",
            "tissue",
            "sample",
            "research",
            "purpose",
            "patient",
            "undergo",
            "surgery",
            "treat",
            "epilepsy",
            "standard",
            "surgical",
            "procedure",
            "medically",
            "intractable",
            "epilepsy",
            "epilepsy",
            "control",
            "medicine",
            "require",
            "removal",
            "brain",
            "tissue",
            "need",
            "diagnostic",
            "study",
            "extra",
            "tissue",
            "would",
            "otherwise",
            "discard",
            "use",
            "research",
            "purpose",
            "addition",
            "blood",
            "vessel",
            "scalp",
            "call",
            "superficial",
            "temporal",
            "artery",
            "also",
            "normally",
            "cut",
            "surgery",
            "piece",
            "vessel",
            "take",
            "research",
            "use",
            "patient",
            "4",
            "year",
            "age",
            "older",
            "undergo",
            "surgery",
            "medically",
            "intractable",
            "epilepsy",
            "may",
            "eligible",
            "study",
            "brain",
            "tissue",
            "collect",
            "protocol",
            "use",
            "study",
            "brain",
            "cell",
            "disease",
            "serotonin",
            "receptor",
            "remain",
            "brain",
            "tissue",
            "freeze",
            "use",
            "future",
            "research",
            "superficial",
            "temporal",
            "artery",
            "use",
            "comparison",
            "carotid",
            "artery",
            "neck",
            "artery",
            "supply",
            "brain",
            "patient",
            "blockage",
            "blood",
            "vessel"
      ],
      "detailed_description": [
            "protocol",
            "perform",
            "research",
            "study",
            "tissue",
            "remove",
            "operate",
            "room",
            "surgical",
            "procedure",
            "medically",
            "intractable",
            "epilepsy",
            "aim",
            "acquire",
            "supply",
            "useful",
            "tissue",
            "specimen",
            "intramural",
            "nih",
            "research",
            "project",
            "investigator",
            "free",
            "select",
            "patient",
            "undergo",
            "surgery",
            "however",
            "total",
            "number",
            "patient",
            "enrol",
            "protocol",
            "restrict",
            "protocol",
            "design",
            "test",
            "new",
            "treatment",
            "treatment",
            "protocol",
            "base",
            "current",
            "standard",
            "care",
            "epilepsy",
            "surgery",
            "goal",
            "surgical",
            "procedure",
            "remove",
            "epileptic",
            "focus",
            "standard",
            "procedure",
            "perform",
            "1",
            "anterior",
            "temporal",
            "lobectomy",
            "2",
            "amygdalohippocampectomy",
            "temporal",
            "lobe",
            "epilepsy",
            "3",
            "focal",
            "cortical",
            "resection",
            "epilepsy",
            "arise",
            "outside",
            "temporal",
            "lobe",
            "research",
            "aspect",
            "protocol",
            "1",
            "brain",
            "tissue",
            "remove",
            "require",
            "diagnostic",
            "study",
            "use",
            "laboratory",
            "study",
            "consistent",
            "institutional",
            "guideline",
            "2",
            "meningeal",
            "sample",
            "dura",
            "take",
            "examine",
            "tissue",
            "marker",
            "lymphatic",
            "vessel",
            "3",
            "blood",
            "test",
            "test",
            "immune",
            "inflammatory",
            "mediator",
            "perform",
            "4",
            "saliva",
            "collect",
            "test",
            "immune",
            "inflammatory",
            "marker",
            "participant",
            "protocol",
            "evaluate",
            "potential",
            "eligibility",
            "ninds",
            "clinical",
            "trial",
            "develop",
            "however",
            "require",
            "enter",
            "protocol",
            "decision",
            "participate",
            "entirely",
            "voluntary",
            "120",
            "patient",
            "accept",
            "protocol"
      ],
      "condition": [],
      "criteria": [
            "inclusion",
            "criterion",
            "eligible",
            "entry",
            "study",
            "candidate",
            "must",
            "meet",
            "al",
            "follow",
            "criterion",
            "1",
            "4",
            "year",
            "age",
            "older",
            "2",
            "simple",
            "complex",
            "partial",
            "seizure",
            "3",
            "seizure",
            "must",
            "persist",
            "despite",
            "medical",
            "therapy",
            "4",
            "able",
            "give",
            "inform",
            "consent",
            "assent",
            "child",
            "5",
            "determine",
            "ninds",
            "neurology",
            "staff",
            "medically",
            "intractable",
            "epilepsy",
            "6",
            "agree",
            "undergo",
            "brain",
            "surgery",
            "treat",
            "medically",
            "intractable",
            "epilepsy",
            "7",
            "agree",
            "allow",
            "tissue",
            "remove",
            "surgery",
            "use",
            "research",
            "exclusion",
            "criterion",
            "candidate",
            "exclude",
            "1",
            "pregnant",
            "woman",
            "childbearing",
            "age",
            "test",
            "urine",
            "pregnancy",
            "test",
            "agree",
            "avoid",
            "pregnant",
            "practice",
            "reliable",
            "form",
            "contraception",
            "abstinence",
            "sexual",
            "intercourse",
            "2",
            "mri",
            "scan",
            "determine",
            "radiologist",
            "3",
            "bleed",
            "disorder",
            "correct",
            "test",
            "treatment",
            "4",
            "unable",
            "understand",
            "risk",
            "test",
            "surgical",
            "therapy",
            "clinical",
            "neuropsychologist",
            "investigator",
            "protocol",
            "examine",
            "patient",
            "epilepsy",
            "surgery",
            "determine",
            "subject",
            "unable",
            "understand",
            "risk",
            "unable",
            "reach",
            "reasonable",
            "decision",
            "incompetent",
            "give",
            "inform",
            "consent"
      ],
      "gender": "All",
      "minimum_age": [
            "4",
            "year"
      ],
      "maximum_age": [],
      "healthy_volunteers": "No",
      "keyword": [
            "intractable",
            "epilepsy"
      ],
      "mesh_term": [],
      "id": "NCT00025714"
}